dziuba_fast_hist_lab2/__init__.py
dziuba_fast_hist_lab2/fast_hist.py
dziuba_fast_hist_lab2-0.1.5.dist-info/METADATA
dziuba_fast_hist_lab2-0.1.5.dist-info/WHEEL
dziuba_fast_hist_lab2-0.1.5.dist-info/top_level.txt
dziuba_fast_hist_lab2-0.1.5.dist-info/RECORD
