Metadata-Version: 2.1
Name: dziuba-fast-hist-lab2
Version: 0.1.5
Summary: UNKNOWN
Home-page: UNKNOWN
Author: Maria Dziuba
Author-email: UNKNOWN
License: UNKNOWN
Platform: UNKNOWN
Requires-Dist: numpy (<1.17)
